README.md
setup.py
tt_cli/__init__.py
tt_cli/cli.py
tt_cli/constants.py
tt_cli/utils.py
tt_cli.egg-info/PKG-INFO
tt_cli.egg-info/SOURCES.txt
tt_cli.egg-info/dependency_links.txt
tt_cli.egg-info/entry_points.txt
tt_cli.egg-info/top_level.txt
tt_cli/commands/__init__.py
tt_cli/commands/abc.py
tt_cli/commands/add.py
tt_cli/commands/clear.py
tt_cli/commands/days.py
tt_cli/commands/show.py