Metadata-Version: 1.1
Name: tt-cli
Version: 1.1
Summary: Simple commandline timetracker
Home-page: https://github.com/a1fred/tt
Author: a1fred
Author-email: demalf@gmail.com
License: MIT
Platform: UNKNOWN
Classifier: Environment :: Console
Classifier: Operating System :: POSIX :: Linux
Classifier: Operating System :: MacOS :: MacOS X
Classifier: Development Status :: 4 - Beta
Classifier: Programming Language :: Python :: 3.5
Classifier: Programming Language :: Python :: 3.6
